[
    {
        "id": "no_tournament",
        "label": "Aucune compétition ouverte",
        "checks": [
            { "source": "session", "key": "TourId", "op": "lte", "value": 0 }
        ]
    },
    {
        "id": "tournament_open",
        "label": "Compétition ouverte",
        "checks": [
            { "source": "session", "key": "TourId", "op": "gt", "value": 0 }
        ]
    },
    {
        "id": "tournament_fr_rules",
        "label": "Compétition avec règles françaises",
        "checks": [
            { "source": "session", "key": "TourId", "op": "gt", "value": 0 },
            {
                "table": "Tournament",
                "column": "ToLocalRule",
                "join": "ToId = TourId",
                "op": "eq",
                "value": "1"
            }
        ]
    },
    {
        "id": "tournament_tae",
        "label": "Compétition avec discipline TAE",
        "checks": [
            { "source": "session", "key": "TourId", "op": "gt", "value": 0 },
            {
                "table": "Tournament",
                "column": "ToType",
                "join": "ToId = TourId",
                "op": "eq",
                "value": "3"
            }
        ]
    },
    {
        "id": "has_individual_duel",
        "label": "Compétition avec duel individuel configuré",
        "checks": [
            { "source": "session", "key": "TourId", "op": "gt", "value": 0 },
            {
                "table": "Event",
                "aggregate": "count",
                "where": [
                    { "column": "EvTournament", "source": "session", "key": "TourId" },
                    { "column": "EvFinalFirstPhase", "op": "neq", "value": "0" },
                    { "column": "EvTeamEvent", "op": "eq", "value": "0" }
                ],
                "op": "gt",
                "value": 0
            }
        ]
    },
    {
        "id": "has_team_duel",
        "label": "Compétition avec duel équipe configuré",
        "checks": [
            { "source": "session", "key": "TourId", "op": "gt", "value": 0 },
            {
                "table": "Event",
                "aggregate": "count",
                "where": [
                    { "column": "EvTournament", "source": "session", "key": "TourId" },
                    { "column": "EvFinalFirstPhase", "op": "neq", "value": "0" },
                    { "column": "EvTeamEvent", "op": "eq", "value": "1" }
                ],
                "op": "gt",
                "value": 0
            }
        ]
    }
]
